{
    "Australi": [
        {
            "beforeCloze": "muszę polecieć do",
            "afterCloze": "ale nie wiem jak mogę dostać~się na lotnisko",
            "clozeWord": "Australi",
            "inUse": "False"
        },
        {
            "beforeCloze": "chciałbym polecieć do",
            "afterCloze": "ponieważ mam bilet i dużo pieniędzy",
            "clozeWord": "Australi",
            "inUse": "False"
        },
        {
            "beforeCloze": "gdzie jest lotnisko? muszę lecieć do",
            "afterCloze": "",
            "clozeWord": "Australi",
            "inUse": "False"
        }
    ],
    "Bangkok": [
        {
            "beforeCloze": "czy wiesz gdzie jest",
            "afterCloze": "",
            "clozeWord": "Bangkok?",
            "inUse": "False"
        }
    ],
    "Bangkoku": [
        {
            "beforeCloze": "muszę jechać do",
            "afterCloze": "ale nie wiem jak mogę dostać~się tam",
            "clozeWord": "Bangkoku",
            "inUse": "False"
        }
    ],
    "Berlina": [
        {
            "beforeCloze": "jak mogę dostać~się do",
            "afterCloze": "",
            "clozeWord": "Berlina?",
            "inUse": "False"
        },
        {
            "beforeCloze": "muszę jechać do",
            "afterCloze": "ale nie wiem jak mogę dostać~się tam",
            "clozeWord": "Berlina",
            "inUse": "False"
        },
        {
            "beforeCloze": "chciałbym polecieć do",
            "afterCloze": "ponieważ mam bilet",
            "clozeWord": "Berlina",
            "inUse": "False"
        }
    ],
    "Brazyli": [
        {
            "beforeCloze": "muszę polecieć do",
            "afterCloze": "ale nie wiem jak mogę dostać~się na lotnisko",
            "clozeWord": "Brazyli",
            "inUse": "False"
        }
    ],
    "Hiszpani": [
        {
            "beforeCloze": "jak mogę dostać~się do",
            "afterCloze": "",
            "clozeWord": "Hiszpani?",
            "inUse": "False"
        },
        {
            "beforeCloze": "muszę polecieć do",
            "afterCloze": "ale nie wiem jak mogę dostać~się na lotnisko",
            "clozeWord": "Hiszpani",
            "inUse": "False"
        },
        {
            "beforeCloze": "chciałbym polecieć do",
            "afterCloze": "mam bilet ale niewiem gdzie jest lotnisko",
            "clozeWord": "Hiszpani",
            "inUse": "False"
        }
    ],
    "Krakowa": [
        {
            "beforeCloze": "muszę jechać do",
            "afterCloze": "ale nie wiem jak mogę dostać~się tam",
            "clozeWord": "Krakowa",
            "inUse": "False"
        }
    ],
    "Polski": [
        {
            "beforeCloze": "chciałbym polecieć do",
            "afterCloze": "ponieważ mam bilet",
            "clozeWord": "Polski",
            "inUse": "False"
        }
    ],
    "Rzeszowa": [
        {
            "beforeCloze": "muszę jechać do",
            "afterCloze": "ale nie wiem jak mogę dostać~się tam",
            "clozeWord": "Rzeszowa",
            "inUse": "False"
        }
    ],
    "Warszawy": [
        {
            "beforeCloze": "jak mogę dostać~się do",
            "afterCloze": "",
            "clozeWord": "Warszawy?",
            "inUse": "False"
        },
        {
            "beforeCloze": "muszę jechać do",
            "afterCloze": "ale nie wiem jak mogę dostać~się tam",
            "clozeWord": "Warszawy",
            "inUse": "False"
        }
    ],
    "Włoch": [
        {
            "beforeCloze": "muszę polecieć do",
            "afterCloze": "ale nie wiem jak mogę dostać~się na lotnisko",
            "clozeWord": "Włoch",
            "inUse": "False"
        },
        {
            "beforeCloze": "muszę polecieć do",
            "afterCloze": "",
            "clozeWord": "Włoch",
            "inUse": "False"
        }
    ],
    "ale": [
        {
            "beforeCloze": "muszę jechać na lotnisko",
            "afterCloze": "nie wiem jak mogę się tam dostać",
            "clozeWord": "ale",
            "inUse": "False"
        },
        {
            "beforeCloze": "przepraszam",
            "afterCloze": "nie dosłyszałem co powiedziałeś czy mógłbyś powtórzyć wolniej i głośniej",
            "clozeWord": "ale",
            "inUse": "False"
        },
        {
            "beforeCloze": "chciałbym polecieć do Hiszpani mam bilet",
            "afterCloze": "niewiem gdzie jest lotnisko",
            "clozeWord": "ale",
            "inUse": "False"
        }
    ],
    "apteka": [
        {
            "beforeCloze": "czy on wie gdzie jest",
            "afterCloze": "",
            "clozeWord": "apteka?",
            "inUse": "False"
        },
        {
            "beforeCloze": "przepraszam czy mógłbyś mi powiedzieć gdzie jest",
            "afterCloze": "",
            "clozeWord": "apteka?",
            "inUse": "False"
        },
        {
            "beforeCloze": "",
            "afterCloze": "jest blisko to tylko dziewięćset metrów stád jeśli chcesz możesz pojechać tam rowerem",
            "clozeWord": "apteka",
            "inUse": "False"
        }
    ],
    "apteke": [
        {
            "beforeCloze": "zobaczysz",
            "afterCloze": "po~lewej",
            "clozeWord": "apteke",
            "inUse": "False"
        },
        {
            "beforeCloze": "idź prosto przez trzysta metrów i zobaczysz",
            "afterCloze": "po~prawej",
            "clozeWord": "apteke",
            "inUse": "False"
        }
    ],
    "apteki": [
        {
            "beforeCloze": "jak mogę dostać~się do",
            "afterCloze": "",
            "clozeWord": "apteki?",
            "inUse": "False"
        },
        {
            "beforeCloze": "ona musi iść do",
            "afterCloze": "",
            "clozeWord": "apteki",
            "inUse": "False"
        },
        {
            "beforeCloze": "muszę iść do",
            "afterCloze": "ale nie wiem gdzie jest",
            "clozeWord": "apteki",
            "inUse": "False"
        }
    ],
    "autobusem": [
        {
            "beforeCloze": "możesz pojechać",
            "afterCloze": "",
            "clozeWord": "autobusem",
            "inUse": "False"
        },
        {
            "beforeCloze": "możesz pojechać",
            "afterCloze": "idź prosto przez sto metrów i zobaczysz przystanek po~lewej",
            "clozeWord": "autobusem.",
            "inUse": "False"
        },
        {
            "beforeCloze": "chciałbym pojechać",
            "afterCloze": "do galerii~handlowej",
            "clozeWord": "autobusem",
            "inUse": "False"
        }
    ],
    "bankomatu": [
        {
            "beforeCloze": "czy oni muszą iść do",
            "afterCloze": "",
            "clozeWord": "bankomatu",
            "inUse": "False"
        }
    ],
    "basen": [
        {
            "beforeCloze": "idź prosto przez siedemset metrów potem skręć w lewo i zobaczysz",
            "afterCloze": "po~prawej",
            "clozeWord": "basen",
            "inUse": "False"
        },
        {
            "beforeCloze": "on musi iść na",
            "afterCloze": "",
            "clozeWord": "basen",
            "inUse": "False"
        },
        {
            "beforeCloze": "przepraszam czy mógłbyś mi powiedzieć gdzie jest",
            "afterCloze": "",
            "clozeWord": "basen?",
            "inUse": "False"
        }
    ],
    "bilet": [
        {
            "beforeCloze": "chciałbym pojechać do kina ponieważ mam",
            "afterCloze": "jak mogę się tam dostać?",
            "clozeWord": "bilet.",
            "inUse": "False"
        },
        {
            "beforeCloze": "chciałbym polecieć do Australi ponieważ mam",
            "afterCloze": "i dużo pieniędzy",
            "clozeWord": "bilet",
            "inUse": "False"
        },
        {
            "beforeCloze": "chciałbym polecieć do Hiszpani mam",
            "afterCloze": "ale niewiem gdzie jest lotnisko",
            "clozeWord": "bilet",
            "inUse": "False"
        }
    ],
    "blisko": [
        {
            "beforeCloze": "plaża jest",
            "afterCloze": "jeśli chcesz możesz pójść tam pieszą lub pojechać rowerem",
            "clozeWord": "blisko",
            "inUse": "False"
        },
        {
            "beforeCloze": "apteka jest",
            "afterCloze": "to tylko sześćset metrów stád",
            "clozeWord": "blisko",
            "inUse": "False"
        },
        {
            "beforeCloze": "basen jest",
            "afterCloze": "to tylko dwieście metrów stád jeśli chcesz mogę wytłumaczyć ci drogę. więc idź prosto przez sto metrów potem skręć w prawo i zobaczysz basen po~lewej",
            "clozeWord": "blisko",
            "inUse": "False"
        }
    ],
    "cepen": [
        {
            "beforeCloze": "idź prosto przez dwieście metrów i zobaczysz",
            "afterCloze": "po~prawej",
            "clozeWord": "cepen",
            "inUse": "False"
        },
        {
            "beforeCloze": "czy wiesz gdzie jest",
            "afterCloze": "",
            "clozeWord": "cepen?",
            "inUse": "False"
        },
        {
            "beforeCloze": "przepraszam nie rozumiem czy mógbyś powtórzyć wolniej jak mogę dostać~się na",
            "afterCloze": "",
            "clozeWord": "cepen",
            "inUse": "False"
        }
    ],
    "chcesz": [
        {
            "beforeCloze": "resteuracja jest blisko jeśli",
            "afterCloze": "możesz pójść tam pieszą",
            "clozeWord": "chcesz",
            "inUse": "False"
        },
        {
            "beforeCloze": "plaża jest daleko to około siedem kilometrów stád jeśli",
            "afterCloze": "możesz pojechać tam taksówką",
            "clozeWord": "chcesz",
            "inUse": "False"
        },
        {
            "beforeCloze": "basen jest blisko to tylko dwieście metrów stád jeśli",
            "afterCloze": "mogę wytłumaczyć ci drogę. więc idź prosto przez sto metrów potem skręć w prawo i zobaczysz basen po~lewej",
            "clozeWord": "chcesz",
            "inUse": "False"
        }
    ],
    "chciałaby": [
        {
            "beforeCloze": "ona",
            "afterCloze": "pójść na plażę",
            "clozeWord": "chciałaby",
            "inUse": "False"
        },
        {
            "beforeCloze": "ona",
            "afterCloze": "pojechać w góry",
            "clozeWord": "chciałaby",
            "inUse": "False"
        },
        {
            "beforeCloze": "ona",
            "afterCloze": "pojechać samochodem",
            "clozeWord": "chciałaby",
            "inUse": "False"
        }
    ],
    "chciałby": [
        {
            "beforeCloze": "on",
            "afterCloze": "pojechać do kościoła",
            "clozeWord": "chciałby",
            "inUse": "False"
        },
        {
            "beforeCloze": "on",
            "afterCloze": "pojechać metrem do galerii~handlowej",
            "clozeWord": "chciałby",
            "inUse": "False"
        }
    ],
    "chciałbym": [
        {
            "beforeCloze": "",
            "afterCloze": "pojechać na przystanek~autobusowy",
            "clozeWord": "chciałbym",
            "inUse": "False"
        },
        {
            "beforeCloze": "",
            "afterCloze": "polecieć do Australi ponieważ mam dużo pieniędzy",
            "clozeWord": "chciałbym",
            "inUse": "False"
        },
        {
            "beforeCloze": "",
            "afterCloze": "polecieć do Hiszpani mam bilet ale niewiem gdzie jest lotnisko. jak mogę się tam dostać",
            "clozeWord": "chciałbym",
            "inUse": "False"
        }
    ],
    "chcieliby": [
        {
            "beforeCloze": "oni",
            "afterCloze": "pojechać nad jezioro",
            "clozeWord": "chcieliby",
            "inUse": "False"
        },
        {
            "beforeCloze": "oni",
            "afterCloze": "pojechać w góry",
            "clozeWord": "chcieliby",
            "inUse": "False"
        }
    ],
    "chcielibyśmy": [
        {
            "beforeCloze": "my",
            "afterCloze": "pójść nad jezioro",
            "clozeWord": "chcielibyśmy",
            "inUse": "False"
        },
        {
            "beforeCloze": "my",
            "afterCloze": "pojechać w góry",
            "clozeWord": "chcielibyśmy",
            "inUse": "False"
        }
    ],
    "ci": [
        {
            "beforeCloze": "basen jest blisko to tylko dwieście metrów stád jeśli chcesz mogę wytłumaczyć",
            "afterCloze": "drogę",
            "clozeWord": "ci",
            "inUse": "False"
        },
        {
            "beforeCloze": "basen jest blisko to tylko dwieście metrów stád jeśli chcesz mogę wytłumaczyć",
            "afterCloze": "drogę. więc idź prosto przez sto metrów potem skręć w prawo i zobaczysz basen po~lewej",
            "clozeWord": "ci",
            "inUse": "False"
        }
    ],
    "co": [
        {
            "beforeCloze": "przepraszam ale nie dosłyszałem",
            "afterCloze": "powiedziałeś",
            "clozeWord": "co",
            "inUse": "False"
        },
        {
            "beforeCloze": "przepraszam ale nie dosłyszałem",
            "afterCloze": "powiedziałeś czy mógłbyś powtórzyć głośniej jak mogę dostać~się na lotnisko",
            "clozeWord": "co",
            "inUse": "False"
        },
        {
            "beforeCloze": "przepraszam ale nie dosłyszałem",
            "afterCloze": "powiedziałeś czy mógłbyś powtórzyć wolniej i głośniej gdzie jest galeria~handlowa",
            "clozeWord": "co",
            "inUse": "False"
        }
    ],
    "czterysta": [
        {
            "beforeCloze": "idź prosto przez",
            "afterCloze": "metrów",
            "clozeWord": "czterysta",
            "inUse": "False"
        },
        {
            "beforeCloze": "idź prosto przez",
            "afterCloze": "metrów i zobaczysz kino po~prawej",
            "clozeWord": "czterysta",
            "inUse": "False"
        },
        {
            "beforeCloze": "możesz pojechać metrem. idź prosto przez",
            "afterCloze": "metrów potem skręć w lewo i zobaczysz stację~metra po~lewej",
            "clozeWord": "czterysta",
            "inUse": "False"
        }
    ],
    "czy": [
        {
            "beforeCloze": "",
            "afterCloze": "on musi jechać na lotnisko?",
            "clozeWord": "czy",
            "inUse": "False"
        },
        {
            "beforeCloze": "",
            "afterCloze": "oni muszą iść do kościoła",
            "clozeWord": "czy",
            "inUse": "False"
        },
        {
            "beforeCloze": "przepraszam ale nie dosłyszałem co powiedziałeś",
            "afterCloze": "mógłbyś powtórzyć wolniej i głośniej gdzie jest galeria~handlowa",
            "clozeWord": "czy",
            "inUse": "False"
        }
    ],
    "daleko": [
        {
            "beforeCloze": "stacja~metra jest",
            "afterCloze": "",
            "clozeWord": "daleko",
            "inUse": "False"
        },
        {
            "beforeCloze": "stacja~metra jest",
            "afterCloze": "jeśli chcesz możesz pojechać tam samochodem",
            "clozeWord": "daleko",
            "inUse": "False"
        },
        {
            "beforeCloze": "plaża jest",
            "afterCloze": "to sześć kilometrów stád",
            "clozeWord": "daleko",
            "inUse": "False"
        }
    ],
    "do": [
        {
            "beforeCloze": "muszę iść",
            "afterCloze": "sklepu ale nie wiem gdzie jest",
            "clozeWord": "do",
            "inUse": "False"
        },
        {
            "beforeCloze": "przepraszam czy mógłbyś mi powiedzieć jak mogę dostać~się",
            "afterCloze": "remizy~strażackiej?",
            "clozeWord": "do",
            "inUse": "False"
        },
        {
            "beforeCloze": "chciałbym polecieć",
            "afterCloze": "Australi ponieważ mam bilet i dużo pieniędzy",
            "clozeWord": "do",
            "inUse": "False"
        }
    ],
    "dostać": [
        {
            "beforeCloze": "chciałbym pojechać do kina ponieważ mam bilet. jak mogę się tam",
            "afterCloze": "",
            "clozeWord": "dostać?",
            "inUse": "False"
        },
        {
            "beforeCloze": "chciałbym polecieć do Hiszpani mam bilet ale niewiem gdzie jest lotnisko. jak mogę się tam",
            "afterCloze": "",
            "clozeWord": "dostać",
            "inUse": "False"
        }
    ],
    "dostać~się": [
        {
            "beforeCloze": "jak mogę",
            "afterCloze": "do apteki?",
            "clozeWord": "dostać~się",
            "inUse": "False"
        },
        {
            "beforeCloze": "muszę jechać na lotnisko ale nie wiem jak mogę",
            "afterCloze": "tam dostać",
            "clozeWord": "się",
            "inUse": "False"
        },
        {
            "beforeCloze": "przepraszam czy mógłbyś mi powiedzieć gdzie jest plaża ponieważ muszę",
            "afterCloze": "tam?",
            "clozeWord": "dostać~się",
            "inUse": "False"
        }
    ],
    "dosłyszałem": [
        {
            "beforeCloze": "nie",
            "afterCloze": "",
            "clozeWord": "dosłyszałem",
            "inUse": "False"
        },
        {
            "beforeCloze": "przepraszam ale nie",
            "afterCloze": "co powiedziałeś czy mógłbyś powtórzyć głośniej jak mogę dostać~się na lotnisko",
            "clozeWord": "dosłyszałem",
            "inUse": "False"
        },
        {
            "beforeCloze": "przepraszam ale nie",
            "afterCloze": "co powiedziałeś czy mógłbyś powtórzyć wolniej i głośniej gdzie jest galeria~handlowa",
            "clozeWord": "dosłyszałem",
            "inUse": "False"
        }
    ],
    "drogę": [
        {
            "beforeCloze": "basen jest blisko to tylko dwieście metrów stád jeśli chcesz mogę wytłumaczyć ci",
            "afterCloze": "",
            "clozeWord": "drogę",
            "inUse": "False"
        },
        {
            "beforeCloze": "basen jest blisko to tylko dwieście metrów stád jeśli chcesz mogę wytłumaczyć ci",
            "afterCloze": "więc idź prosto przez sto metrów potem skręć w prawo i zobaczysz basen po~lewej",
            "clozeWord": "drogę.",
            "inUse": "False"
        }
    ],
    "dużo": [
        {
            "beforeCloze": "chciałbym polecieć do Australi ponieważ mam",
            "afterCloze": "pieniędzy",
            "clozeWord": "dużo",
            "inUse": "False"
        },
        {
            "beforeCloze": "chciałbym polecieć do Australi ponieważ mam bilet i",
            "afterCloze": "pieniędzy",
            "clozeWord": "dużo",
            "inUse": "False"
        }
    ],
    "dwieście": [
        {
            "beforeCloze": "idź prosto przez",
            "afterCloze": "metrów i zobaczysz cepen po~prawej",
            "clozeWord": "dwieście",
            "inUse": "False"
        },
        {
            "beforeCloze": "możesz pojechać taksówką. idź prosto przez",
            "afterCloze": "metrów i zobaczysz postój po~lewej",
            "clozeWord": "dwieście",
            "inUse": "False"
        },
        {
            "beforeCloze": "basen jest blisko to tylko",
            "afterCloze": "metrów stád jeśli chcesz mogę wytłumaczyć ci drogę",
            "clozeWord": "dwieście",
            "inUse": "False"
        }
    ],
    "dworzec~autobusowy": [
        {
            "beforeCloze": "zobaczysz",
            "afterCloze": "",
            "clozeWord": "dworzec~autobusowy",
            "inUse": "False"
        },
        {
            "beforeCloze": "nie wiem gdzie jest",
            "afterCloze": "",
            "clozeWord": "dworzec~autobusowy",
            "inUse": "False"
        },
        {
            "beforeCloze": "przepraszam czy mogłabyś mi powiedzieć jak mogę dostać~się na",
            "afterCloze": "",
            "clozeWord": "dworzec~autobusowy?",
            "inUse": "False"
        }
    ],
    "dworzec~kolejowy": [
        {
            "beforeCloze": "jak mogę dostać~się na",
            "afterCloze": "",
            "clozeWord": "dworzec~kolejowy?",
            "inUse": "False"
        },
        {
            "beforeCloze": "idź prosto przez sto metrów i zobaczysz",
            "afterCloze": "po~prawej",
            "clozeWord": "dworzec~kolejowy",
            "inUse": "False"
        },
        {
            "beforeCloze": "czy mógłbyś powtórzyć gdzie jest",
            "afterCloze": "",
            "clozeWord": "dworzec~kolejowy?",
            "inUse": "False"
        }
    ],
    "dworzec~tramwajowy": [
        {
            "beforeCloze": "przepraszam gdzie jest",
            "afterCloze": "",
            "clozeWord": "dworzec~tramwajowy?",
            "inUse": "False"
        }
    ],
    "dziewięćset": [
        {
            "beforeCloze": "idź prosto przez",
            "afterCloze": "metrów potem skręć w prawo i zobaczysz basen po~prawej",
            "clozeWord": "dziewięćset",
            "inUse": "False"
        },
        {
            "beforeCloze": "kino jest",
            "afterCloze": "metrów stád jeśli chcesz możesz pójść tam pieszą",
            "clozeWord": "dziewięćset",
            "inUse": "False"
        },
        {
            "beforeCloze": "apteka jest blisko to tylko",
            "afterCloze": "metrów stád jeśli chcesz możesz pojechać tam rowerem",
            "clozeWord": "dziewięćset",
            "inUse": "False"
        }
    ],
    "galeria~handlowa": [
        {
            "beforeCloze": "czy wiesz gdzie jest",
            "afterCloze": "",
            "clozeWord": "galeria~handlowa?",
            "inUse": "False"
        },
        {
            "beforeCloze": "przepraszam ale nie dosłyszałem co powiedziałeś czy mógłbyś powtórzyć wolniej i głośniej gdzie jest",
            "afterCloze": "",
            "clozeWord": "galeria~handlowa",
            "inUse": "False"
        },
        {
            "beforeCloze": "",
            "afterCloze": "jest dziewięćset metrów stád jeśli chcesz możesz pójść tam pieszą",
            "clozeWord": "galeria~handlowa",
            "inUse": "False"
        }
    ],
    "galerie~handlową": [
        {
            "beforeCloze": "zobaczysz",
            "afterCloze": "",
            "clozeWord": "galerie~handlową",
            "inUse": "False"
        },
        {
            "beforeCloze": "idź prosto przez sto metrów i zobaczysz",
            "afterCloze": "po~prawej",
            "clozeWord": "galerie~handlową",
            "inUse": "False"
        }
    ],
    "galerii~handlowej": [
        {
            "beforeCloze": "jak mogę dostać~się do",
            "afterCloze": "",
            "clozeWord": "galerii~handlowej?",
            "inUse": "False"
        },
        {
            "beforeCloze": "muszę iść do",
            "afterCloze": "ale nie wiem gdzie jest",
            "clozeWord": "galerii~handlowej",
            "inUse": "False"
        },
        {
            "beforeCloze": "on chciałby pojechać metrem do",
            "afterCloze": "",
            "clozeWord": "galerii~handlowej",
            "inUse": "False"
        }
    ],
    "gdzie": [
        {
            "beforeCloze": "ona wie",
            "afterCloze": "jest kino",
            "clozeWord": "gdzie",
            "inUse": "False"
        },
        {
            "beforeCloze": "przepraszam ale nie dosłyszałem co powiedziałeś czy mógłbyś powtórzyć wolniej i głośniej",
            "afterCloze": "jest galeria~handlowa",
            "clozeWord": "gdzie",
            "inUse": "False"
        },
        {
            "beforeCloze": "chciałbym polecieć do Hiszpani mam bilet ale niewiem",
            "afterCloze": "jest lotnisko. jak mogę się tam dostać",
            "clozeWord": "gdzie",
            "inUse": "False"
        }
    ],
    "gdzie~jest": [
        {
            "beforeCloze": "muszę iść do sklepu ale nie wiem",
            "afterCloze": "jest",
            "clozeWord": "gdzie",
            "inUse": "False"
        }
    ],
    "góry": [
        {
            "beforeCloze": "my chcielibyśmy pojechać w",
            "afterCloze": "",
            "clozeWord": "góry",
            "inUse": "False"
        },
        {
            "beforeCloze": "ona chciałaby pojechać w",
            "afterCloze": "",
            "clozeWord": "góry",
            "inUse": "False"
        },
        {
            "beforeCloze": "oni chcieliby pojechać w",
            "afterCloze": "",
            "clozeWord": "góry",
            "inUse": "False"
        }
    ],
    "głośniej": [
        {
            "beforeCloze": "przepraszam ale nie dosłyszałem co powiedziałeś czy mógłbyś powtórzyć",
            "afterCloze": "",
            "clozeWord": "głośniej",
            "inUse": "False"
        },
        {
            "beforeCloze": "przepraszam ale nie dosłyszałem co powiedziałeś czy mógłbyś powtórzyć",
            "afterCloze": "jak mogę dostać~się na lotnisko",
            "clozeWord": "głośniej",
            "inUse": "False"
        },
        {
            "beforeCloze": "przepraszam ale nie dosłyszałem co powiedziałeś czy mógłbyś powtórzyć wolniej i",
            "afterCloze": "gdzie jest galeria~handlowa",
            "clozeWord": "głośniej",
            "inUse": "False"
        }
    ],
    "i": [
        {
            "beforeCloze": "przepraszam ale nie dosłyszałem co powiedziałeś czy mógłbyś powtórzyć wolniej",
            "afterCloze": "głośniej",
            "clozeWord": "i",
            "inUse": "False"
        },
        {
            "beforeCloze": "chciałbym polecieć do Australi ponieważ mam bilet",
            "afterCloze": "dużo pieniędzy",
            "clozeWord": "i",
            "inUse": "False"
        },
        {
            "beforeCloze": "basen jest blisko to tylko dwieście metrów stád jeśli chcesz mogę wytłumaczyć ci drogę. więc idź prosto przez sto metrów potem skręć w prawo",
            "afterCloze": "zobaczysz basen po~lewej",
            "clozeWord": "i",
            "inUse": "False"
        }
    ],
    "idź": [
        {
            "beforeCloze": "",
            "afterCloze": "prosto przez trzysta metrów",
            "clozeWord": "idź",
            "inUse": "False"
        },
        {
            "beforeCloze": "możesz pojechać pociągiem.",
            "afterCloze": "prosto przez sto metrów i zobaczysz stację po~prawej",
            "clozeWord": "idź",
            "inUse": "False"
        },
        {
            "beforeCloze": "basen jest blisko to tylko dwieście metrów stád jeśli chcesz mogę wytłumaczyć ci drogę. więc",
            "afterCloze": "prosto przez sto metrów potem skręć w prawo i zobaczysz basen po~lewej",
            "clozeWord": "idź",
            "inUse": "False"
        }
    ],
    "iść": [
        {
            "beforeCloze": "on musi",
            "afterCloze": "na basen",
            "clozeWord": "iść",
            "inUse": "False"
        },
        {
            "beforeCloze": "czy oni muszą",
            "afterCloze": "do kościoła",
            "clozeWord": "iść",
            "inUse": "False"
        },
        {
            "beforeCloze": "muszę",
            "afterCloze": "do sklepu ale nie wiem gdzie jest",
            "clozeWord": "iść",
            "inUse": "False"
        }
    ],
    "jak": [
        {
            "beforeCloze": "przepraszam czy mógłbyś mi powiedzieć",
            "afterCloze": "mogę dostać~się na na plażę?",
            "clozeWord": "jak",
            "inUse": "False"
        },
        {
            "beforeCloze": "chciałbym polecieć do Hiszpani mam bilet ale niewiem gdzie jest lotnisko.",
            "afterCloze": "mogę się tam dostać",
            "clozeWord": "jak",
            "inUse": "False"
        },
        {
            "beforeCloze": "przepraszam nie rozumiem czy mógbyś powtórzyć wolniej",
            "afterCloze": "mogę dostać~się do remizy~strażackiej",
            "clozeWord": "jak",
            "inUse": "False"
        }
    ],
    "jechać": [
        {
            "beforeCloze": "ona musi",
            "afterCloze": "do sklepu~spożywczego",
            "clozeWord": "jechać",
            "inUse": "False"
        },
        {
            "beforeCloze": "my musimy",
            "afterCloze": "na lotnisko",
            "clozeWord": "jechać",
            "inUse": "False"
        },
        {
            "beforeCloze": "muszę",
            "afterCloze": "do Warszawy ale nie wiem jak mogę dostać~się tam",
            "clozeWord": "jechać",
            "inUse": "False"
        }
    ],
    "jest": [
        {
            "beforeCloze": "przepraszam czy mógłbyś mi powiedzieć gdzie",
            "afterCloze": "szpital ponieważ muszę tam pojechać?",
            "clozeWord": "jest",
            "inUse": "False"
        },
        {
            "beforeCloze": "chciałbym polecieć do Hiszpani mam bilet ale niewiem gdzie",
            "afterCloze": "lotnisko",
            "clozeWord": "jest",
            "inUse": "False"
        },
        {
            "beforeCloze": "basen",
            "afterCloze": "blisko to tylko dwieście metrów stád jeśli chcesz mogę wytłumaczyć ci drogę. więc idź prosto przez sto metrów potem skręć w prawo i zobaczysz basen po~lewej",
            "clozeWord": "jest",
            "inUse": "False"
        }
    ],
    "jeszcze~raz": [
        {
            "beforeCloze": "czy mógbyś powtórzyć",
            "afterCloze": "",
            "clozeWord": "jeszcze~raz",
            "inUse": "False"
        },
        {
            "beforeCloze": "przepraszam nie rozumiem czy mógbyś powtórzyć",
            "afterCloze": "",
            "clozeWord": "jeszcze~raz",
            "inUse": "False"
        },
        {
            "beforeCloze": "przepraszam nie rozumiem czy mógbyś powtórzyć",
            "afterCloze": "jak mogę dostać~się do kościoła",
            "clozeWord": "jeszcze~raz",
            "inUse": "False"
        }
    ],
    "jezioro": [
        {
            "beforeCloze": "my chcielibyśmy pójść nad",
            "afterCloze": "",
            "clozeWord": "jezioro",
            "inUse": "False"
        },
        {
            "beforeCloze": "oni chcieliby pojechać nad",
            "afterCloze": "",
            "clozeWord": "jezioro",
            "inUse": "False"
        },
        {
            "beforeCloze": "",
            "afterCloze": "jest blisko jeśli chcesz możesz pójść tam pieszą",
            "clozeWord": "jezioro",
            "inUse": "False"
        }
    ],
    "jeśli": [
        {
            "beforeCloze": "resteuracja jest blisko",
            "afterCloze": "chcesz możesz pójść tam pieszą",
            "clozeWord": "jeśli",
            "inUse": "False"
        },
        {
            "beforeCloze": "plaża jest daleko to około siedem kilometrów stád",
            "afterCloze": "chcesz możesz pojechać tam taksówką",
            "clozeWord": "jeśli",
            "inUse": "False"
        },
        {
            "beforeCloze": "basen jest blisko to tylko dwieście metrów stád",
            "afterCloze": "chcesz mogę wytłumaczyć ci drogę. więc idź prosto przez sto metrów potem skręć w prawo i zobaczysz basen po~lewej",
            "clozeWord": "jeśli",
            "inUse": "False"
        }
    ],
    "kilometrów": [
        {
            "beforeCloze": "plaża jest daleko to sześć",
            "afterCloze": "stád",
            "clozeWord": "kilometrów",
            "inUse": "False"
        },
        {
            "beforeCloze": "plaża jest daleko to około siedem",
            "afterCloze": "stád jeśli chcesz możesz pojechać tam taksówką",
            "clozeWord": "kilometrów",
            "inUse": "False"
        }
    ],
    "kina": [
        {
            "beforeCloze": "muszę jechać do",
            "afterCloze": "",
            "clozeWord": "kina",
            "inUse": "False"
        },
        {
            "beforeCloze": "oni muszą iść do",
            "afterCloze": "",
            "clozeWord": "kina",
            "inUse": "False"
        },
        {
            "beforeCloze": "chciałbym pojechać do",
            "afterCloze": "ponieważ mam bilet. jak mogę się tam dostać?",
            "clozeWord": "kina",
            "inUse": "False"
        }
    ],
    "kino": [
        {
            "beforeCloze": "idź prosto przez czterysta metrów i zobaczysz",
            "afterCloze": "po~prawej",
            "clozeWord": "kino",
            "inUse": "False"
        },
        {
            "beforeCloze": "przepraszam czy mógłbyś mi powiedzieć gdzie jest",
            "afterCloze": "",
            "clozeWord": "kino?",
            "inUse": "False"
        },
        {
            "beforeCloze": "",
            "afterCloze": "jest dziewięćset metrów stád jeśli chcesz możesz pójść tam pieszą",
            "clozeWord": "kino",
            "inUse": "False"
        }
    ],
    "kościoła": [
        {
            "beforeCloze": "muszę iść do",
            "afterCloze": "ale nie wiem gdzie jest",
            "clozeWord": "kościoła",
            "inUse": "False"
        },
        {
            "beforeCloze": "on chciałby pojechać do",
            "afterCloze": "",
            "clozeWord": "kościoła",
            "inUse": "False"
        },
        {
            "beforeCloze": "przepraszam nie rozumiem czy mógbyś powtórzyć jeszcze~raz jak mogę dostać~się do",
            "afterCloze": "",
            "clozeWord": "kościoła",
            "inUse": "False"
        }
    ],
    "lecieć": [
        {
            "beforeCloze": "gdzie jest lotnisko? muszę",
            "afterCloze": "do Australi",
            "clozeWord": "lecieć",
            "inUse": "False"
        }
    ],
    "lewo": [
        {
            "beforeCloze": "idź prosto przez siedemset metrów potem skręć w",
            "afterCloze": "i zobaczysz basen po~prawej",
            "clozeWord": "lewo",
            "inUse": "False"
        },
        {
            "beforeCloze": "idź prosto przez osiemset metrów potem skręć w",
            "afterCloze": "i zobaczysz basen po~prawej",
            "clozeWord": "lewo",
            "inUse": "False"
        },
        {
            "beforeCloze": "możesz pojechać metrem. idź prosto przez czterysta metrów potem skręć w",
            "afterCloze": "i zobaczysz stację~metra po~lewej",
            "clozeWord": "lewo",
            "inUse": "False"
        }
    ],
    "lotnisko": [
        {
            "beforeCloze": "możesz polecieć samolotem. idź prosto przez siedemset metrów potem skręć w prawo i zobaczysz",
            "afterCloze": "po~lewej",
            "clozeWord": "lotnisko",
            "inUse": "False"
        },
        {
            "beforeCloze": "przepraszam ale nie dosłyszałem co powiedziałeś czy mógłbyś powtórzyć głośniej jak mogę dostać~się na",
            "afterCloze": "",
            "clozeWord": "lotnisko",
            "inUse": "False"
        },
        {
            "beforeCloze": "gdzie jest",
            "afterCloze": "muszę lecieć do Australi",
            "clozeWord": "lotnisko?",
            "inUse": "False"
        }
    ],
    "lub": [
        {
            "beforeCloze": "plaża jest blisko jeśli chcesz możesz pójść tam pieszą",
            "afterCloze": "pojechać rowerem",
            "clozeWord": "lub",
            "inUse": "False"
        },
        {
            "beforeCloze": "możesz pójść tam pieszą",
            "afterCloze": "pojechać rowerem",
            "clozeWord": "lub",
            "inUse": "False"
        }
    ],
    "mam": [
        {
            "beforeCloze": "chciałbym pojechać do kina ponieważ",
            "afterCloze": "bilet. jak mogę się tam dostać?",
            "clozeWord": "mam",
            "inUse": "False"
        },
        {
            "beforeCloze": "chciałbym polecieć do Australi ponieważ",
            "afterCloze": "dużo pieniędzy",
            "clozeWord": "mam",
            "inUse": "False"
        },
        {
            "beforeCloze": "chciałbym polecieć do Hiszpani",
            "afterCloze": "bilet ale niewiem gdzie jest lotnisko",
            "clozeWord": "mam",
            "inUse": "False"
        }
    ],
    "metrem": [
        {
            "beforeCloze": "możesz pojechać",
            "afterCloze": "",
            "clozeWord": "metrem",
            "inUse": "False"
        },
        {
            "beforeCloze": "możesz pojechać",
            "afterCloze": "idź prosto przez czterysta metrów potem skręć w lewo i zobaczysz stację~metra po~lewej",
            "clozeWord": "metrem.",
            "inUse": "False"
        },
        {
            "beforeCloze": "on chciałby pojechać",
            "afterCloze": "do galerii~handlowej",
            "clozeWord": "metrem",
            "inUse": "False"
        }
    ],
    "metrów": [
        {
            "beforeCloze": "idź prosto przez siedemset",
            "afterCloze": "potem skręć w lewo i zobaczysz basen po~prawej",
            "clozeWord": "metrów",
            "inUse": "False"
        },
        {
            "beforeCloze": "muzeum jest pięćset",
            "afterCloze": "stád jeśli chcesz możesz pójść tam pieszą",
            "clozeWord": "metrów",
            "inUse": "False"
        },
        {
            "beforeCloze": "apteka jest blisko to tylko sześćset",
            "afterCloze": "stád",
            "clozeWord": "metrów",
            "inUse": "False"
        }
    ],
    "mi": [
        {
            "beforeCloze": "przepraszam czy mogłabyś",
            "afterCloze": "powiedzieć gdzie jest kino?",
            "clozeWord": "mi",
            "inUse": "False"
        },
        {
            "beforeCloze": "przepraszam czy mógłbyś",
            "afterCloze": "powiedzieć gdzie jest lotnisko ponieważ muszę tam pojechać?",
            "clozeWord": "mi",
            "inUse": "False"
        },
        {
            "beforeCloze": "przepraszam czy mógłbyś",
            "afterCloze": "powiedzieć jak mogę dostać~się na na plażę?",
            "clozeWord": "mi",
            "inUse": "False"
        }
    ],
    "miasta": [
        {
            "beforeCloze": "oni muszą iść do",
            "afterCloze": "",
            "clozeWord": "miasta",
            "inUse": "False"
        }
    ],
    "miejsce": [
        {
            "beforeCloze": "czy wiesz gdzie jest to",
            "afterCloze": "",
            "clozeWord": "miejsce?",
            "inUse": "False"
        }
    ],
    "mogliby": [
        {
            "beforeCloze": "przepraszam nie rozumiem czy oni",
            "afterCloze": "powtórzyć wolniej",
            "clozeWord": "mogliby",
            "inUse": "False"
        }
    ],
    "mogę": [
        {
            "beforeCloze": "przepraszam ale nie dosłyszałem co powiedziałeś czy mógłbyś powtórzyć głośniej jak",
            "afterCloze": "dostać~się na lotnisko",
            "clozeWord": "mogę",
            "inUse": "False"
        },
        {
            "beforeCloze": "chciałbym pojechać do kina ponieważ mam bilet. jak",
            "afterCloze": "się tam dostać?",
            "clozeWord": "mogę",
            "inUse": "False"
        },
        {
            "beforeCloze": "basen jest blisko to tylko dwieście metrów stád jeśli chcesz",
            "afterCloze": "wytłumaczyć ci drogę. więc idź prosto przez sto metrów potem skręć w prawo i zobaczysz basen po~lewej",
            "clozeWord": "mogę",
            "inUse": "False"
        }
    ],
    "mogłabyś": [
        {
            "beforeCloze": "przepraszam czy",
            "afterCloze": "mi powiedzieć gdzie jest kino?",
            "clozeWord": "mogłabyś",
            "inUse": "False"
        },
        {
            "beforeCloze": "przepraszam czy",
            "afterCloze": "mi powiedzieć jak mogę dostać~się na dworzec~autobusowy?",
            "clozeWord": "mogłabyś",
            "inUse": "False"
        }
    ],
    "możesz": [
        {
            "beforeCloze": "",
            "afterCloze": "pojechać autobusem",
            "clozeWord": "możesz",
            "inUse": "False"
        },
        {
            "beforeCloze": "",
            "afterCloze": "polecieć samolotem. idź prosto przez siedemset metrów potem skręć w prawo i zobaczysz lotnisko po~lewej",
            "clozeWord": "możesz",
            "inUse": "False"
        },
        {
            "beforeCloze": "plaża jest blisko jeśli chcesz",
            "afterCloze": "pójść tam pieszą",
            "clozeWord": "możesz",
            "inUse": "False"
        }
    ],
    "musi": [
        {
            "beforeCloze": "on",
            "afterCloze": "iść na basen",
            "clozeWord": "musi",
            "inUse": "False"
        },
        {
            "beforeCloze": "ona",
            "afterCloze": "jechać do sklepu~spożywczego",
            "clozeWord": "musi",
            "inUse": "False"
        },
        {
            "beforeCloze": "czy on",
            "afterCloze": "jechać na lotnisko?",
            "clozeWord": "musi",
            "inUse": "False"
        }
    ],
    "musimy": [
        {
            "beforeCloze": "my",
            "afterCloze": "iść do galerii~handlowej",
            "clozeWord": "musimy",
            "inUse": "False"
        },
        {
            "beforeCloze": "my",
            "afterCloze": "jechać na lotnisko",
            "clozeWord": "musimy",
            "inUse": "False"
        },
        {
            "beforeCloze": "czy",
            "afterCloze": "iść na cepen",
            "clozeWord": "musimy",
            "inUse": "False"
        }
    ],
    "musisz": [
        {
            "beforeCloze": "czy",
            "afterCloze": "iść do kina?",
            "clozeWord": "musisz",
            "inUse": "False"
        },
        {
            "beforeCloze": "czy",
            "afterCloze": "iść do apteki?",
            "clozeWord": "musisz",
            "inUse": "False"
        },
        {
            "beforeCloze": "czy",
            "afterCloze": "jechać na lotnisko?",
            "clozeWord": "musisz",
            "inUse": "False"
        }
    ],
    "muszą": [
        {
            "beforeCloze": "oni",
            "afterCloze": "iść do kina",
            "clozeWord": "muszą",
            "inUse": "False"
        },
        {
            "beforeCloze": "oni",
            "afterCloze": "iść do kościoła",
            "clozeWord": "muszą",
            "inUse": "False"
        },
        {
            "beforeCloze": "czy oni",
            "afterCloze": "iść na lotnisko",
            "clozeWord": "muszą",
            "inUse": "False"
        }
    ],
    "muszę": [
        {
            "beforeCloze": "",
            "afterCloze": "iść do apteki",
            "clozeWord": "muszę",
            "inUse": "False"
        },
        {
            "beforeCloze": "",
            "afterCloze": "jechać na lotnisko ale nie wiem jak mogę się tam dostać",
            "clozeWord": "muszę",
            "inUse": "False"
        },
        {
            "beforeCloze": "przepraszam czy mógłbyś mi powiedzieć gdzie jest szpital ponieważ",
            "afterCloze": "tam pojechać?",
            "clozeWord": "muszę",
            "inUse": "False"
        }
    ],
    "muzeum": [
        {
            "beforeCloze": "czy ona musi iść do",
            "afterCloze": "",
            "clozeWord": "muzeum",
            "inUse": "False"
        },
        {
            "beforeCloze": "przepraszam czy mógłbyś mi powiedzieć gdzie jest",
            "afterCloze": "ponieważ muszę tam pojechać?",
            "clozeWord": "muzeum",
            "inUse": "False"
        },
        {
            "beforeCloze": "",
            "afterCloze": "jest pięćset metrów stád jeśli chcesz możesz pójść tam pieszą",
            "clozeWord": "muzeum",
            "inUse": "False"
        }
    ],
    "my": [
        {
            "beforeCloze": "",
            "afterCloze": "musimy iść do galerii~handlowej",
            "clozeWord": "my",
            "inUse": "False"
        },
        {
            "beforeCloze": "",
            "afterCloze": "nie wiemy gdzie jest szpital",
            "clozeWord": "my",
            "inUse": "False"
        },
        {
            "beforeCloze": "",
            "afterCloze": "chcielibyśmy pójść nad jezioro",
            "clozeWord": "my",
            "inUse": "False"
        }
    ],
    "mógbyś": [
        {
            "beforeCloze": "przepraszam nie rozumiem czy",
            "afterCloze": "powtórzyć wolniej jak mogę dostać~się na lotnisko",
            "clozeWord": "mógbyś",
            "inUse": "False"
        },
        {
            "beforeCloze": "przepraszam nie rozumiem czy",
            "afterCloze": "powtórzyć wolniej jak mogę dostać~się do remizy~strażackiej",
            "clozeWord": "mógbyś",
            "inUse": "False"
        },
        {
            "beforeCloze": "czy",
            "afterCloze": "powtórzyć jeszcze~raz",
            "clozeWord": "mógbyś",
            "inUse": "False"
        }
    ],
    "mógłaby": [
        {
            "beforeCloze": "przepraszam nie rozumiem czy ona",
            "afterCloze": "powtórzyć wolniej",
            "clozeWord": "mógłaby",
            "inUse": "False"
        }
    ],
    "mógłby": [
        {
            "beforeCloze": "przepraszam nie rozumiem czy on",
            "afterCloze": "powtórzyć wolniej",
            "clozeWord": "mógłby",
            "inUse": "False"
        }
    ],
    "mógłbyś": [
        {
            "beforeCloze": "przepraszam czy",
            "afterCloze": "mi powiedzieć jak mogę dostać~się na na plażę?",
            "clozeWord": "mógłbyś",
            "inUse": "False"
        },
        {
            "beforeCloze": "czy",
            "afterCloze": "powtórzyć gdzie jest przystanek~autobusowy?",
            "clozeWord": "mógłbyś",
            "inUse": "False"
        },
        {
            "beforeCloze": "przepraszam ale nie dosłyszałem co powiedziałeś czy",
            "afterCloze": "powtórzyć wolniej i głośniej",
            "clozeWord": "mógłbyś",
            "inUse": "False"
        }
    ],
    "na": [
        {
            "beforeCloze": "ona musi jechać",
            "afterCloze": "basen",
            "clozeWord": "na",
            "inUse": "False"
        },
        {
            "beforeCloze": "czy oni muszą iść",
            "afterCloze": "dworzec~kolejowy",
            "clozeWord": "na",
            "inUse": "False"
        },
        {
            "beforeCloze": "muszę polecieć do Hiszpani ale nie wiem jak mogę dostać~się",
            "afterCloze": "lotnisko",
            "clozeWord": "na",
            "inUse": "False"
        }
    ],
    "nad": [
        {
            "beforeCloze": "chciałbym pojechać",
            "afterCloze": "jezioro",
            "clozeWord": "nad",
            "inUse": "False"
        },
        {
            "beforeCloze": "my chcielibyśmy pójść",
            "afterCloze": "jezioro",
            "clozeWord": "nad",
            "inUse": "False"
        },
        {
            "beforeCloze": "oni chcieliby pojechać",
            "afterCloze": "jezioro",
            "clozeWord": "nad",
            "inUse": "False"
        }
    ],
    "nie": [
        {
            "beforeCloze": "on",
            "afterCloze": "wie gdzie jest plaża",
            "clozeWord": "nie",
            "inUse": "False"
        },
        {
            "beforeCloze": "muszę jechać na lotnisko ale",
            "afterCloze": "wiem jak mogę się tam dostać",
            "clozeWord": "nie",
            "inUse": "False"
        },
        {
            "beforeCloze": "przepraszam",
            "afterCloze": "rozumiem czy ona mógłaby powtórzyć wolniej",
            "clozeWord": "nie",
            "inUse": "False"
        }
    ],
    "niewiem": [
        {
            "beforeCloze": "chciałbym polecieć do Hiszpani mam bilet ale",
            "afterCloze": "gdzie jest lotnisko",
            "clozeWord": "niewiem",
            "inUse": "False"
        },
        {
            "beforeCloze": "chciałbym polecieć do Hiszpani mam bilet ale",
            "afterCloze": "gdzie jest lotnisko. jak mogę się tam dostać",
            "clozeWord": "niewiem",
            "inUse": "False"
        }
    ],
    "około": [
        {
            "beforeCloze": "plaża jest daleko to",
            "afterCloze": "siedem kilometrów stád jeśli chcesz możesz pojechać tam taksówką",
            "clozeWord": "około",
            "inUse": "False"
        }
    ],
    "on": [
        {
            "beforeCloze": "",
            "afterCloze": "musi iść na basen",
            "clozeWord": "on",
            "inUse": "False"
        },
        {
            "beforeCloze": "",
            "afterCloze": "chciałby pojechać metrem do galerii~handlowej",
            "clozeWord": "on",
            "inUse": "False"
        },
        {
            "beforeCloze": "przepraszam nie rozumiem czy",
            "afterCloze": "mógłby powtórzyć wolniej",
            "clozeWord": "on",
            "inUse": "False"
        }
    ],
    "ona": [
        {
            "beforeCloze": "",
            "afterCloze": "musi jechać na basen",
            "clozeWord": "ona",
            "inUse": "False"
        },
        {
            "beforeCloze": "",
            "afterCloze": "wie gdzie jest kino",
            "clozeWord": "ona",
            "inUse": "False"
        },
        {
            "beforeCloze": "przepraszam nie rozumiem czy",
            "afterCloze": "mógłaby powtórzyć wolniej",
            "clozeWord": "ona",
            "inUse": "False"
        }
    ],
    "oni": [
        {
            "beforeCloze": "",
            "afterCloze": "muszą iść do kina",
            "clozeWord": "oni",
            "inUse": "False"
        },
        {
            "beforeCloze": "",
            "afterCloze": "wiedzą gdzie jest sklep~spożywczy",
            "clozeWord": "oni",
            "inUse": "False"
        },
        {
            "beforeCloze": "przepraszam nie rozumiem czy",
            "afterCloze": "mogliby powtórzyć wolniej",
            "clozeWord": "oni",
            "inUse": "False"
        }
    ],
    "osiemset": [
        {
            "beforeCloze": "idź prosto przez",
            "afterCloze": "metrów",
            "clozeWord": "osiemset",
            "inUse": "False"
        },
        {
            "beforeCloze": "idź prosto przez",
            "afterCloze": "metrów i zobaczysz basen po~lewej",
            "clozeWord": "osiemset",
            "inUse": "False"
        },
        {
            "beforeCloze": "idź prosto przez",
            "afterCloze": "metrów potem skręć w lewo i zobaczysz basen po~prawej",
            "clozeWord": "osiemset",
            "inUse": "False"
        }
    ],
    "pieniędzy": [
        {
            "beforeCloze": "chciałbym polecieć do Australi ponieważ mam dużo",
            "afterCloze": "",
            "clozeWord": "pieniędzy",
            "inUse": "False"
        },
        {
            "beforeCloze": "chciałbym polecieć do Australi ponieważ mam bilet i dużo",
            "afterCloze": "",
            "clozeWord": "pieniędzy",
            "inUse": "False"
        }
    ],
    "pieszą": [
        {
            "beforeCloze": "muzeum jest pięćset metrów stád jeśli chcesz możesz pójść tam",
            "afterCloze": "",
            "clozeWord": "pieszą",
            "inUse": "False"
        },
        {
            "beforeCloze": "plaża jest blisko jeśli chcesz możesz pójść tam",
            "afterCloze": "",
            "clozeWord": "pieszą",
            "inUse": "False"
        },
        {
            "beforeCloze": "możesz pójść tam",
            "afterCloze": "lub pojechać rowerem",
            "clozeWord": "pieszą",
            "inUse": "False"
        }
    ],
    "pięćset": [
        {
            "beforeCloze": "idź prosto przez",
            "afterCloze": "metrów i zobaczysz postój~taksówek po~prawej",
            "clozeWord": "pięćset",
            "inUse": "False"
        },
        {
            "beforeCloze": "możesz pojechać metrem. idź prosto przez",
            "afterCloze": "metrów potem skręć w prawo i zobaczysz stację~metra po~lewej",
            "clozeWord": "pięćset",
            "inUse": "False"
        },
        {
            "beforeCloze": "muzeum jest",
            "afterCloze": "metrów stád jeśli chcesz możesz pójść tam pieszą",
            "clozeWord": "pięćset",
            "inUse": "False"
        }
    ],
    "plaża": [
        {
            "beforeCloze": "przepraszam czy mógłbyś mi powiedzieć gdzie jest",
            "afterCloze": "ponieważ muszę dostać~się tam?",
            "clozeWord": "plaża",
            "inUse": "False"
        },
        {
            "beforeCloze": "",
            "afterCloze": "jest blisko jeśli chcesz możesz pójść tam pieszą lub pojechać rowerem",
            "clozeWord": "plaża",
            "inUse": "False"
        },
        {
            "beforeCloze": "",
            "afterCloze": "jest daleko to sześć kilometrów stád",
            "clozeWord": "plaża",
            "inUse": "False"
        }
    ],
    "plażę": [
        {
            "beforeCloze": "czy musimy iść na",
            "afterCloze": "",
            "clozeWord": "plażę",
            "inUse": "False"
        },
        {
            "beforeCloze": "przepraszam czy mógłbyś mi powiedzieć jak mogę dostać~się na na",
            "afterCloze": "",
            "clozeWord": "plażę?",
            "inUse": "False"
        },
        {
            "beforeCloze": "ona chciałaby pójść na",
            "afterCloze": "",
            "clozeWord": "plażę",
            "inUse": "False"
        }
    ],
    "pociągiem": [
        {
            "beforeCloze": "możesz pojechać",
            "afterCloze": "",
            "clozeWord": "pociągiem",
            "inUse": "False"
        },
        {
            "beforeCloze": "możesz pojechać",
            "afterCloze": "idź prosto przez sto metrów i zobaczysz stację po~prawej",
            "clozeWord": "pociągiem.",
            "inUse": "False"
        }
    ],
    "poczta": [
        {
            "beforeCloze": "",
            "afterCloze": "jest blisko jeśli chcesz możesz pojechać tam rowerem",
            "clozeWord": "poczta",
            "inUse": "False"
        }
    ],
    "pocztę": [
        {
            "beforeCloze": "on musi iść na",
            "afterCloze": "",
            "clozeWord": "pocztę",
            "inUse": "False"
        }
    ],
    "pojechać": [
        {
            "beforeCloze": "możesz",
            "afterCloze": "metrem. idź prosto przez czterysta metrów potem skręć w lewo i zobaczysz stację~metra po~lewej",
            "clozeWord": "pojechać",
            "inUse": "False"
        },
        {
            "beforeCloze": "przepraszam czy mógłbyś mi powiedzieć gdzie jest lotnisko ponieważ muszę tam",
            "afterCloze": "",
            "clozeWord": "pojechać?",
            "inUse": "False"
        },
        {
            "beforeCloze": "on chciałby",
            "afterCloze": "do kościoła",
            "clozeWord": "pojechać",
            "inUse": "False"
        }
    ],
    "polecieć": [
        {
            "beforeCloze": "możesz",
            "afterCloze": "samolotem. idź prosto przez siedemset metrów potem skręć w prawo i zobaczysz lotnisko po~lewej",
            "clozeWord": "polecieć",
            "inUse": "False"
        },
        {
            "beforeCloze": "muszę",
            "afterCloze": "do Hiszpani ale nie wiem jak mogę dostać~się na lotnisko",
            "clozeWord": "polecieć",
            "inUse": "False"
        },
        {
            "beforeCloze": "chciałbym",
            "afterCloze": "do Australi ponieważ mam dużo pieniędzy",
            "clozeWord": "polecieć",
            "inUse": "False"
        }
    ],
    "ponieważ": [
        {
            "beforeCloze": "przepraszam czy mógłbyś mi powiedzieć gdzie jest plaża",
            "afterCloze": "muszę dostać~się tam?",
            "clozeWord": "ponieważ",
            "inUse": "False"
        },
        {
            "beforeCloze": "chciałbym pojechać do kina",
            "afterCloze": "mam bilet. jak mogę się tam dostać?",
            "clozeWord": "ponieważ",
            "inUse": "False"
        },
        {
            "beforeCloze": "chciałbym polecieć do Australi",
            "afterCloze": "mam dużo pieniędzy",
            "clozeWord": "ponieważ",
            "inUse": "False"
        }
    ],
    "postój": [
        {
            "beforeCloze": "możesz pojechać taksówką. idź prosto przez dwieście metrów i zobaczysz",
            "afterCloze": "po~lewej",
            "clozeWord": "postój",
            "inUse": "False"
        },
        {
            "beforeCloze": "możesz pojechać taksówką. idź prosto przez dwieście metrów i zobaczysz",
            "afterCloze": "po~prawej",
            "clozeWord": "postój",
            "inUse": "False"
        }
    ],
    "postój~taksówek": [
        {
            "beforeCloze": "idź prosto przez pięćset metrów i zobaczysz",
            "afterCloze": "po~prawej",
            "clozeWord": "postój~taksówek",
            "inUse": "False"
        },
        {
            "beforeCloze": "oni wiedzą gdzie jest",
            "afterCloze": "",
            "clozeWord": "postój~taksówek",
            "inUse": "False"
        },
        {
            "beforeCloze": "czy wiesz gdzie jest",
            "afterCloze": "",
            "clozeWord": "postój~taksówek?",
            "inUse": "False"
        }
    ],
    "potem": [
        {
            "beforeCloze": "możesz pojechać metrem. idź prosto przez czterysta metrów",
            "afterCloze": "skręć w lewo i zobaczysz stację~metra po~lewej",
            "clozeWord": "potem",
            "inUse": "False"
        },
        {
            "beforeCloze": "możesz polecieć samolotem. idź prosto przez siedemset metrów",
            "afterCloze": "skręć w prawo i zobaczysz lotnisko po~lewej",
            "clozeWord": "potem",
            "inUse": "False"
        },
        {
            "beforeCloze": "basen jest blisko to tylko dwieście metrów stád jeśli chcesz mogę wytłumaczyć ci drogę. więc idź prosto przez sto metrów",
            "afterCloze": "skręć w prawo i zobaczysz basen po~lewej",
            "clozeWord": "potem",
            "inUse": "False"
        }
    ],
    "powiedziałeś": [
        {
            "beforeCloze": "przepraszam ale nie dosłyszałem co",
            "afterCloze": "",
            "clozeWord": "powiedziałeś",
            "inUse": "False"
        },
        {
            "beforeCloze": "przepraszam ale nie dosłyszałem co",
            "afterCloze": "czy mógłbyś powtórzyć głośniej jak mogę dostać~się na lotnisko",
            "clozeWord": "powiedziałeś",
            "inUse": "False"
        },
        {
            "beforeCloze": "przepraszam ale nie dosłyszałem co",
            "afterCloze": "czy mógłbyś powtórzyć wolniej i głośniej gdzie jest galeria~handlowa",
            "clozeWord": "powiedziałeś",
            "inUse": "False"
        }
    ],
    "powiedzieć": [
        {
            "beforeCloze": "przepraszam czy mogłabyś mi",
            "afterCloze": "gdzie jest kino?",
            "clozeWord": "powiedzieć",
            "inUse": "False"
        },
        {
            "beforeCloze": "przepraszam czy mógłbyś mi",
            "afterCloze": "gdzie jest lotnisko ponieważ muszę tam pojechać?",
            "clozeWord": "powiedzieć",
            "inUse": "False"
        },
        {
            "beforeCloze": "przepraszam czy mógłbyś mi",
            "afterCloze": "jak mogę dostać~się na na plażę?",
            "clozeWord": "powiedzieć",
            "inUse": "False"
        }
    ],
    "powtórzyć": [
        {
            "beforeCloze": "czy mógłbyś",
            "afterCloze": "gdzie jest przystanek~autobusowy?",
            "clozeWord": "powtórzyć",
            "inUse": "False"
        },
        {
            "beforeCloze": "przepraszam ale nie dosłyszałem co powiedziałeś czy mógłbyś",
            "afterCloze": "wolniej i głośniej",
            "clozeWord": "powtórzyć",
            "inUse": "False"
        },
        {
            "beforeCloze": "przepraszam nie rozumiem czy mógbyś",
            "afterCloze": "jeszcze~raz jak mogę dostać~się do kościoła",
            "clozeWord": "powtórzyć",
            "inUse": "False"
        }
    ],
    "po~lewej": [
        {
            "beforeCloze": "zobaczysz kino",
            "afterCloze": "",
            "clozeWord": "po~lewej",
            "inUse": "False"
        },
        {
            "beforeCloze": "możesz pojechać metrem. idź prosto przez trzysta metrów i zobaczysz stację~metra",
            "afterCloze": "",
            "clozeWord": "po~lewej",
            "inUse": "False"
        },
        {
            "beforeCloze": "basen jest blisko to tylko dwieście metrów stád jeśli chcesz mogę wytłumaczyć ci drogę. więc idź prosto przez sto metrów potem skręć w prawo i zobaczysz basen",
            "afterCloze": "",
            "clozeWord": "po~lewej",
            "inUse": "False"
        }
    ],
    "po~prawej": [
        {
            "beforeCloze": "zobaczysz cepen",
            "afterCloze": "",
            "clozeWord": "po~prawej",
            "inUse": "False"
        },
        {
            "beforeCloze": "idź prosto przez siedemset metrów potem skręć w lewo i zobaczysz basen",
            "afterCloze": "",
            "clozeWord": "po~prawej",
            "inUse": "False"
        },
        {
            "beforeCloze": "możesz pojechać pociągiem. idź prosto przez sto metrów i zobaczysz stację",
            "afterCloze": "",
            "clozeWord": "po~prawej",
            "inUse": "False"
        }
    ],
    "prawo": [
        {
            "beforeCloze": "możesz pojechać metrem. idź prosto przez sześćset metrów potem skręć w",
            "afterCloze": "i zobaczysz stację~metra po~prawej",
            "clozeWord": "prawo",
            "inUse": "False"
        },
        {
            "beforeCloze": "możesz polecieć samolotem. idź prosto przez siedemset metrów potem skręć w",
            "afterCloze": "i zobaczysz lotnisko po~lewej",
            "clozeWord": "prawo",
            "inUse": "False"
        },
        {
            "beforeCloze": "basen jest blisko to tylko dwieście metrów stád jeśli chcesz mogę wytłumaczyć ci drogę. więc idź prosto przez sto metrów potem skręć w",
            "afterCloze": "i zobaczysz basen po~lewej",
            "clozeWord": "prawo",
            "inUse": "False"
        }
    ],
    "prosto": [
        {
            "beforeCloze": "idź",
            "afterCloze": "przez trzysta metrów",
            "clozeWord": "prosto",
            "inUse": "False"
        },
        {
            "beforeCloze": "możesz pojechać pociągiem. idź",
            "afterCloze": "przez sto metrów i zobaczysz stację po~prawej",
            "clozeWord": "prosto",
            "inUse": "False"
        },
        {
            "beforeCloze": "basen jest blisko to tylko dwieście metrów stád jeśli chcesz mogę wytłumaczyć ci drogę. więc idź",
            "afterCloze": "przez sto metrów potem skręć w prawo i zobaczysz basen po~lewej",
            "clozeWord": "prosto",
            "inUse": "False"
        }
    ],
    "przepraszam": [
        {
            "beforeCloze": "",
            "afterCloze": "gdzie jest lotnisko?",
            "clozeWord": "przepraszam",
            "inUse": "False"
        },
        {
            "beforeCloze": "",
            "afterCloze": "czy mógłbyś mi powiedzieć jak mogę dostać~się na na plażę?",
            "clozeWord": "przepraszam",
            "inUse": "False"
        },
        {
            "beforeCloze": "",
            "afterCloze": "ale nie dosłyszałem co powiedziałeś",
            "clozeWord": "przepraszam",
            "inUse": "False"
        }
    ],
    "przez": [
        {
            "beforeCloze": "idź prosto",
            "afterCloze": "trzysta metrów",
            "clozeWord": "przez",
            "inUse": "False"
        },
        {
            "beforeCloze": "możesz pojechać pociągiem. idź prosto",
            "afterCloze": "sto metrów i zobaczysz stację po~prawej",
            "clozeWord": "przez",
            "inUse": "False"
        },
        {
            "beforeCloze": "basen jest blisko to tylko dwieście metrów stád jeśli chcesz mogę wytłumaczyć ci drogę. więc idź prosto",
            "afterCloze": "sto metrów potem skręć w prawo i zobaczysz basen po~lewej",
            "clozeWord": "przez",
            "inUse": "False"
        }
    ],
    "przystanek": [
        {
            "beforeCloze": "możesz pojechać autobusem. idź prosto przez sto metrów i zobaczysz",
            "afterCloze": "po~lewej",
            "clozeWord": "przystanek",
            "inUse": "False"
        }
    ],
    "przystanek~autobusowy": [
        {
            "beforeCloze": "on musi iść na",
            "afterCloze": "",
            "clozeWord": "przystanek~autobusowy",
            "inUse": "False"
        },
        {
            "beforeCloze": "nie wiem gdzie jest",
            "afterCloze": "",
            "clozeWord": "przystanek~autobusowy",
            "inUse": "False"
        },
        {
            "beforeCloze": "przepraszam czy mógłbyś mi powiedzieć jak mogę dostać~się na",
            "afterCloze": "",
            "clozeWord": "przystanek~autobusowy?",
            "inUse": "False"
        }
    ],
    "pójść": [
        {
            "beforeCloze": "ona chciałaby",
            "afterCloze": "na plażę",
            "clozeWord": "pójść",
            "inUse": "False"
        },
        {
            "beforeCloze": "my chcielibyśmy",
            "afterCloze": "nad jezioro",
            "clozeWord": "pójść",
            "inUse": "False"
        },
        {
            "beforeCloze": "plaża jest blisko jeśli chcesz możesz",
            "afterCloze": "tam pieszą lub pojechać rowerem",
            "clozeWord": "pójść",
            "inUse": "False"
        }
    ],
    "remiza~strażacka": [
        {
            "beforeCloze": "ona nie wie gdzie jest",
            "afterCloze": "",
            "clozeWord": "remiza~strażacka",
            "inUse": "False"
        },
        {
            "beforeCloze": "przepraszam czy mógłbyś mi powiedzieć gdzie jest",
            "afterCloze": "",
            "clozeWord": "remiza~strażacka?",
            "inUse": "False"
        },
        {
            "beforeCloze": "",
            "afterCloze": "jest sześćset metrów stád jeśli chcesz możesz pójść tam pieszą",
            "clozeWord": "remiza~strażacka",
            "inUse": "False"
        }
    ],
    "remizy~strażackiej": [
        {
            "beforeCloze": "przepraszam czy mógłbyś mi powiedzieć jak mogę dostać~się do",
            "afterCloze": "",
            "clozeWord": "remizy~strażackiej?",
            "inUse": "False"
        },
        {
            "beforeCloze": "przepraszam nie rozumiem czy mógbyś powtórzyć wolniej jak mogę dostać~się do",
            "afterCloze": "",
            "clozeWord": "remizy~strażackiej",
            "inUse": "False"
        }
    ],
    "resteuracja": [
        {
            "beforeCloze": "wiem gdzie jest",
            "afterCloze": "",
            "clozeWord": "resteuracja",
            "inUse": "False"
        },
        {
            "beforeCloze": "",
            "afterCloze": "jest blisko jeśli chcesz możesz pójść tam pieszą",
            "clozeWord": "resteuracja",
            "inUse": "False"
        }
    ],
    "rowerem": [
        {
            "beforeCloze": "możesz pojechać",
            "afterCloze": "",
            "clozeWord": "rowerem",
            "inUse": "False"
        },
        {
            "beforeCloze": "możesz pójść tam pieszą lub pojechać",
            "afterCloze": "",
            "clozeWord": "rowerem",
            "inUse": "False"
        },
        {
            "beforeCloze": "apteka jest blisko to tylko dziewięćset metrów stád jeśli chcesz możesz pojechać tam",
            "afterCloze": "",
            "clozeWord": "rowerem",
            "inUse": "False"
        }
    ],
    "rozumiem": [
        {
            "beforeCloze": "przepraszam nie",
            "afterCloze": "",
            "clozeWord": "rozumiem",
            "inUse": "False"
        },
        {
            "beforeCloze": "przepraszam nie",
            "afterCloze": "czy on mógłby powtórzyć wolniej",
            "clozeWord": "rozumiem",
            "inUse": "False"
        },
        {
            "beforeCloze": "przepraszam nie",
            "afterCloze": "czy mógbyś powtórzyć jeszcze~raz jak mogę dostać~się do kościoła",
            "clozeWord": "rozumiem",
            "inUse": "False"
        }
    ],
    "samochodem": [
        {
            "beforeCloze": "możesz pojechać",
            "afterCloze": "",
            "clozeWord": "samochodem",
            "inUse": "False"
        },
        {
            "beforeCloze": "ona chciałaby pojechać",
            "afterCloze": "",
            "clozeWord": "samochodem",
            "inUse": "False"
        },
        {
            "beforeCloze": "stacja~metra jest daleko jeśli chcesz możesz pojechać tam",
            "afterCloze": "",
            "clozeWord": "samochodem",
            "inUse": "False"
        }
    ],
    "samolotem": [
        {
            "beforeCloze": "możesz polecieć",
            "afterCloze": "idź prosto przez siedemset metrów potem skręć w prawo i zobaczysz lotnisko po~lewej",
            "clozeWord": "samolotem.",
            "inUse": "False"
        }
    ],
    "siedem": [
        {
            "beforeCloze": "plaża jest daleko to około",
            "afterCloze": "kilometrów stád jeśli chcesz możesz pojechać tam taksówką",
            "clozeWord": "siedem",
            "inUse": "False"
        }
    ],
    "siedemset": [
        {
            "beforeCloze": "idź prosto przez",
            "afterCloze": "metrów i zobaczysz basen po~prawej",
            "clozeWord": "siedemset",
            "inUse": "False"
        },
        {
            "beforeCloze": "możesz polecieć samolotem. idź prosto przez",
            "afterCloze": "metrów potem skręć w prawo i zobaczysz lotnisko po~lewej",
            "clozeWord": "siedemset",
            "inUse": "False"
        },
        {
            "beforeCloze": "plaża jest",
            "afterCloze": "metrów stád jeśli chcesz możesz pójść tam",
            "clozeWord": "siedemset",
            "inUse": "False"
        }
    ],
    "się": [
        {
            "beforeCloze": "chciałbym pojechać do kina ponieważ mam bilet. jak mogę",
            "afterCloze": "tam dostać?",
            "clozeWord": "się",
            "inUse": "False"
        },
        {
            "beforeCloze": "chciałbym polecieć do Hiszpani mam bilet ale niewiem gdzie jest lotnisko. jak mogę",
            "afterCloze": "tam dostać",
            "clozeWord": "się",
            "inUse": "False"
        }
    ],
    "sklepu": [
        {
            "beforeCloze": "muszę iść do",
            "afterCloze": "ale nie wiem gdzie jest",
            "clozeWord": "sklepu",
            "inUse": "False"
        }
    ],
    "sklepu~spożywczego": [
        {
            "beforeCloze": "muszę iść do",
            "afterCloze": "",
            "clozeWord": "sklepu~spożywczego",
            "inUse": "False"
        },
        {
            "beforeCloze": "ona musi jechać do",
            "afterCloze": "",
            "clozeWord": "sklepu~spożywczego",
            "inUse": "False"
        }
    ],
    "sklep~spożywczy": [
        {
            "beforeCloze": "wiem gdzie jest",
            "afterCloze": "",
            "clozeWord": "sklep~spożywczy",
            "inUse": "False"
        },
        {
            "beforeCloze": "oni wiedzą gdzie jest",
            "afterCloze": "",
            "clozeWord": "sklep~spożywczy",
            "inUse": "False"
        }
    ],
    "skręć": [
        {
            "beforeCloze": "możesz pojechać metrem. idź prosto przez czterysta metrów potem",
            "afterCloze": "w lewo i zobaczysz stację~metra po~lewej",
            "clozeWord": "skręć",
            "inUse": "False"
        },
        {
            "beforeCloze": "możesz polecieć samolotem. idź prosto przez siedemset metrów potem",
            "afterCloze": "w prawo i zobaczysz lotnisko po~lewej",
            "clozeWord": "skręć",
            "inUse": "False"
        },
        {
            "beforeCloze": "basen jest blisko to tylko dwieście metrów stád jeśli chcesz mogę wytłumaczyć ci drogę. więc idź prosto przez sto metrów potem",
            "afterCloze": "w prawo i zobaczysz basen po~lewej",
            "clozeWord": "skręć",
            "inUse": "False"
        }
    ],
    "stacja~metra": [
        {
            "beforeCloze": "on nie wie gdzie jest",
            "afterCloze": "",
            "clozeWord": "stacja~metra",
            "inUse": "False"
        },
        {
            "beforeCloze": "czy ona wie gdzie jest",
            "afterCloze": "",
            "clozeWord": "stacja~metra?",
            "inUse": "False"
        },
        {
            "beforeCloze": "",
            "afterCloze": "jest daleko jeśli chcesz możesz pojechać tam samochodem",
            "clozeWord": "stacja~metra",
            "inUse": "False"
        }
    ],
    "stację": [
        {
            "beforeCloze": "możesz pojechać pociągiem. idź prosto przez sto metrów i zobaczysz",
            "afterCloze": "po~prawej",
            "clozeWord": "stację",
            "inUse": "False"
        }
    ],
    "stację~autobusową": [
        {
            "beforeCloze": "idź prosto przez sto metrów i zobaczysz",
            "afterCloze": "",
            "clozeWord": "stację~autobusową",
            "inUse": "False"
        },
        {
            "beforeCloze": "idź prosto przez sto metrów i zobaczysz",
            "afterCloze": "po~lewej",
            "clozeWord": "stację~autobusową",
            "inUse": "False"
        }
    ],
    "stację~metra": [
        {
            "beforeCloze": "możesz pojechać metrem. idź prosto przez czterysta metrów potem skręć w lewo i zobaczysz",
            "afterCloze": "po~lewej",
            "clozeWord": "stację~metra",
            "inUse": "False"
        },
        {
            "beforeCloze": "my musimy iść na",
            "afterCloze": "",
            "clozeWord": "stację~metra",
            "inUse": "False"
        },
        {
            "beforeCloze": "przepraszam nie rozumiem czy mógbyś powtórzyć wolniej jak mogę dostać~się na",
            "afterCloze": "",
            "clozeWord": "stację~metra",
            "inUse": "False"
        }
    ],
    "sto": [
        {
            "beforeCloze": "idź prosto przez",
            "afterCloze": "metrów",
            "clozeWord": "sto",
            "inUse": "False"
        },
        {
            "beforeCloze": "możesz pojechać pociągiem. idź prosto przez",
            "afterCloze": "metrów i zobaczysz stację po~prawej",
            "clozeWord": "sto",
            "inUse": "False"
        },
        {
            "beforeCloze": "basen jest blisko to tylko dwieście metrów stád jeśli chcesz mogę wytłumaczyć ci drogę. więc idź prosto przez",
            "afterCloze": "metrów potem skręć w prawo i zobaczysz basen po~lewej",
            "clozeWord": "sto",
            "inUse": "False"
        }
    ],
    "stád": [
        {
            "beforeCloze": "muzeum jest pięćset metrów",
            "afterCloze": "jeśli chcesz możesz pójść tam pieszą",
            "clozeWord": "stád",
            "inUse": "False"
        },
        {
            "beforeCloze": "plaża jest daleko to sześć kilometrów",
            "afterCloze": "",
            "clozeWord": "stád",
            "inUse": "False"
        },
        {
            "beforeCloze": "basen jest blisko to tylko dwieście metrów",
            "afterCloze": "jeśli chcesz mogę wytłumaczyć ci drogę. więc idź prosto przez sto metrów potem skręć w prawo i zobaczysz basen po~lewej",
            "clozeWord": "stád",
            "inUse": "False"
        }
    ],
    "sześć": [
        {
            "beforeCloze": "plaża jest daleko to",
            "afterCloze": "kilometrów stád",
            "clozeWord": "sześć",
            "inUse": "False"
        }
    ],
    "sześćset": [
        {
            "beforeCloze": "możesz pojechać metrem. idź prosto przez",
            "afterCloze": "metrów potem skręć w prawo i zobaczysz stację~metra po~prawej",
            "clozeWord": "sześćset",
            "inUse": "False"
        },
        {
            "beforeCloze": "remiza~strażacka jest",
            "afterCloze": "metrów stád jeśli chcesz możesz pójść tam pieszą",
            "clozeWord": "sześćset",
            "inUse": "False"
        },
        {
            "beforeCloze": "apteka jest blisko to tylko",
            "afterCloze": "metrów stád",
            "clozeWord": "sześćset",
            "inUse": "False"
        }
    ],
    "szpital": [
        {
            "beforeCloze": "my nie wiemy gdzie jest",
            "afterCloze": "",
            "clozeWord": "szpital",
            "inUse": "False"
        },
        {
            "beforeCloze": "przepraszam czy mógłbyś mi powiedzieć gdzie jest",
            "afterCloze": "ponieważ muszę tam pojechać?",
            "clozeWord": "szpital",
            "inUse": "False"
        }
    ],
    "taksówką": [
        {
            "beforeCloze": "możesz pojechać",
            "afterCloze": "",
            "clozeWord": "taksówką",
            "inUse": "False"
        },
        {
            "beforeCloze": "możesz pojechać",
            "afterCloze": "idź prosto przez dwieście metrów i zobaczysz postój po~lewej",
            "clozeWord": "taksówką.",
            "inUse": "False"
        },
        {
            "beforeCloze": "plaża jest daleko to około siedem kilometrów stád jeśli chcesz możesz pojechać tam",
            "afterCloze": "",
            "clozeWord": "taksówką",
            "inUse": "False"
        }
    ],
    "tam": [
        {
            "beforeCloze": "muszę jechać na lotnisko ale nie wiem jak mogę się",
            "afterCloze": "dostać",
            "clozeWord": "tam",
            "inUse": "False"
        },
        {
            "beforeCloze": "przepraszam czy mógłbyś mi powiedzieć gdzie jest plaża ponieważ muszę dostać~się",
            "afterCloze": "",
            "clozeWord": "tam?",
            "inUse": "False"
        },
        {
            "beforeCloze": "możesz pójść",
            "afterCloze": "pieszą lub pojechać rowerem",
            "clozeWord": "tam",
            "inUse": "False"
        }
    ],
    "to": [
        {
            "beforeCloze": "czy wiesz gdzie jest",
            "afterCloze": "miejsce?",
            "clozeWord": "to",
            "inUse": "False"
        },
        {
            "beforeCloze": "plaża jest daleko",
            "afterCloze": "około siedem kilometrów stád jeśli chcesz możesz pojechać tam taksówką",
            "clozeWord": "to",
            "inUse": "False"
        },
        {
            "beforeCloze": "basen jest blisko",
            "afterCloze": "tylko dwieście metrów stád jeśli chcesz mogę wytłumaczyć ci drogę. więc idź prosto przez sto metrów potem skręć w prawo i zobaczysz basen po~lewej",
            "clozeWord": "to",
            "inUse": "False"
        }
    ],
    "toaleta": [
        {
            "beforeCloze": "przepraszam gdzie jest",
            "afterCloze": "",
            "clozeWord": "toaleta?",
            "inUse": "False"
        },
        {
            "beforeCloze": "czy wiesz gdzie jest",
            "afterCloze": "",
            "clozeWord": "toaleta?",
            "inUse": "False"
        }
    ],
    "toalety": [
        {
            "beforeCloze": "muszę iść do",
            "afterCloze": "",
            "clozeWord": "toalety",
            "inUse": "False"
        }
    ],
    "tramwajem": [
        {
            "beforeCloze": "możesz pojechać",
            "afterCloze": "",
            "clozeWord": "tramwajem",
            "inUse": "False"
        }
    ],
    "trzysta": [
        {
            "beforeCloze": "idź prosto przez",
            "afterCloze": "metrów i zobaczysz apteke po~prawej",
            "clozeWord": "trzysta",
            "inUse": "False"
        },
        {
            "beforeCloze": "możesz pojechać metrem. idź prosto przez",
            "afterCloze": "metrów i zobaczysz stację~metra po~lewej",
            "clozeWord": "trzysta",
            "inUse": "False"
        },
        {
            "beforeCloze": "basen jest",
            "afterCloze": "metrów stád jeśli chcesz możesz pójść tam",
            "clozeWord": "trzysta",
            "inUse": "False"
        }
    ],
    "tylko": [
        {
            "beforeCloze": "apteka jest blisko to",
            "afterCloze": "sześćset metrów stád",
            "clozeWord": "tylko",
            "inUse": "False"
        },
        {
            "beforeCloze": "apteka jest blisko to",
            "afterCloze": "dziewięćset metrów stád jeśli chcesz możesz pojechać tam rowerem",
            "clozeWord": "tylko",
            "inUse": "False"
        },
        {
            "beforeCloze": "basen jest blisko to",
            "afterCloze": "dwieście metrów stád jeśli chcesz mogę wytłumaczyć ci drogę. więc idź prosto przez sto metrów potem skręć w prawo i zobaczysz basen po~lewej",
            "clozeWord": "tylko",
            "inUse": "False"
        }
    ],
    "w": [
        {
            "beforeCloze": "możesz polecieć samolotem. idź prosto przez siedemset metrów potem skręć",
            "afterCloze": "prawo i zobaczysz lotnisko po~lewej",
            "clozeWord": "w",
            "inUse": "False"
        },
        {
            "beforeCloze": "my chcielibyśmy pojechać",
            "afterCloze": "góry",
            "clozeWord": "w",
            "inUse": "False"
        },
        {
            "beforeCloze": "basen jest blisko to tylko dwieście metrów stád jeśli chcesz mogę wytłumaczyć ci drogę. więc idź prosto przez sto metrów potem skręć",
            "afterCloze": "prawo i zobaczysz basen po~lewej",
            "clozeWord": "w",
            "inUse": "False"
        }
    ],
    "wie": [
        {
            "beforeCloze": "ona",
            "afterCloze": "gdzie jest kino",
            "clozeWord": "wie",
            "inUse": "False"
        },
        {
            "beforeCloze": "on nie",
            "afterCloze": "gdzie jest plaża",
            "clozeWord": "wie",
            "inUse": "False"
        },
        {
            "beforeCloze": "czy on",
            "afterCloze": "gdzie jest apteka?",
            "clozeWord": "wie",
            "inUse": "False"
        }
    ],
    "wiedzą": [
        {
            "beforeCloze": "oni",
            "afterCloze": "gdzie jest sklep~spożywczy",
            "clozeWord": "wiedzą",
            "inUse": "False"
        },
        {
            "beforeCloze": "oni",
            "afterCloze": "gdzie jest postój~taksówek",
            "clozeWord": "wiedzą",
            "inUse": "False"
        },
        {
            "beforeCloze": "czy oni",
            "afterCloze": "gdzie jest plaża?",
            "clozeWord": "wiedzą",
            "inUse": "False"
        }
    ],
    "wiem": [
        {
            "beforeCloze": "",
            "afterCloze": "gdzie jest basen",
            "clozeWord": "wiem",
            "inUse": "False"
        },
        {
            "beforeCloze": "muszę jechać na lotnisko ale nie",
            "afterCloze": "jak mogę się tam dostać",
            "clozeWord": "wiem",
            "inUse": "False"
        },
        {
            "beforeCloze": "muszę polecieć do Hiszpani ale nie",
            "afterCloze": "jak mogę dostać~się na lotnisko",
            "clozeWord": "wiem",
            "inUse": "False"
        }
    ],
    "wiemy": [
        {
            "beforeCloze": "my nie",
            "afterCloze": "gdzie jest szpital",
            "clozeWord": "wiemy",
            "inUse": "False"
        }
    ],
    "wiesz": [
        {
            "beforeCloze": "czy",
            "afterCloze": "gdzie jest Bangkok?",
            "clozeWord": "wiesz",
            "inUse": "False"
        },
        {
            "beforeCloze": "czy",
            "afterCloze": "gdzie jest basen?",
            "clozeWord": "wiesz",
            "inUse": "False"
        },
        {
            "beforeCloze": "czy",
            "afterCloze": "gdzie jest to miejsce?",
            "clozeWord": "wiesz",
            "inUse": "False"
        }
    ],
    "więc": [
        {
            "beforeCloze": "basen jest blisko to tylko dwieście metrów stád jeśli chcesz mogę wytłumaczyć ci drogę.",
            "afterCloze": "idź prosto przez sto metrów potem skręć w prawo i zobaczysz basen po~lewej",
            "clozeWord": "więc",
            "inUse": "False"
        }
    ],
    "wolniej": [
        {
            "beforeCloze": "przepraszam ale nie dosłyszałem co powiedziałeś czy mógłbyś powtórzyć",
            "afterCloze": "i głośniej gdzie jest galeria~handlowa",
            "clozeWord": "wolniej",
            "inUse": "False"
        },
        {
            "beforeCloze": "przepraszam nie rozumiem czy on mógłby powtórzyć",
            "afterCloze": "",
            "clozeWord": "wolniej",
            "inUse": "False"
        },
        {
            "beforeCloze": "przepraszam nie rozumiem czy mógbyś powtórzyć",
            "afterCloze": "jak mogę dostać~się na lotnisko",
            "clozeWord": "wolniej",
            "inUse": "False"
        }
    ],
    "wytłumaczyć": [
        {
            "beforeCloze": "basen jest blisko to tylko dwieście metrów stád jeśli chcesz mogę",
            "afterCloze": "ci drogę",
            "clozeWord": "wytłumaczyć",
            "inUse": "False"
        },
        {
            "beforeCloze": "basen jest blisko to tylko dwieście metrów stád jeśli chcesz mogę",
            "afterCloze": "ci drogę. więc idź prosto przez sto metrów potem skręć w prawo i zobaczysz basen po~lewej",
            "clozeWord": "wytłumaczyć",
            "inUse": "False"
        }
    ],
    "zobaczysz": [
        {
            "beforeCloze": "",
            "afterCloze": "przystanek~autobusowy",
            "clozeWord": "zobaczysz",
            "inUse": "False"
        },
        {
            "beforeCloze": "",
            "afterCloze": "cepen po~prawej",
            "clozeWord": "zobaczysz",
            "inUse": "False"
        },
        {
            "beforeCloze": "basen jest blisko to tylko dwieście metrów stád jeśli chcesz mogę wytłumaczyć ci drogę. więc idź prosto przez sto metrów potem skręć w prawo i",
            "afterCloze": "basen po~lewej",
            "clozeWord": "zobaczysz",
            "inUse": "False"
        }
    ],
    "zoo": [
        {
            "beforeCloze": "oni muszą iść do",
            "afterCloze": "",
            "clozeWord": "zoo",
            "inUse": "False"
        },
        {
            "beforeCloze": "czy ona musi iść do",
            "afterCloze": "",
            "clozeWord": "zoo",
            "inUse": "False"
        }
    ]
}